pybible/__init__.py
pybible/__main__.py
pybible/pybible_load.py
pybible/classes/__init__.py
pybible/classes/bible.py
pybible/classes/book.py
pybible/classes/chapter.py
pybible/classes/verse.py
pybible/resources/__init__.py
pybible/resources/bibles_json/__init__.py
pybible/resources/bibles_json/kj.json
pybible/resources/bibles_json/kj/1chronicles.json
pybible/resources/bibles_json/kj/1corinthians.json
pybible/resources/bibles_json/kj/1john.json
pybible/resources/bibles_json/kj/1kings.json
pybible/resources/bibles_json/kj/1peter.json
pybible/resources/bibles_json/kj/1samuel.json
pybible/resources/bibles_json/kj/1thessalonians.json
pybible/resources/bibles_json/kj/1timothy.json
pybible/resources/bibles_json/kj/2chronicles.json
pybible/resources/bibles_json/kj/2corinthians.json
pybible/resources/bibles_json/kj/2john.json
pybible/resources/bibles_json/kj/2kings.json
pybible/resources/bibles_json/kj/2peter.json
pybible/resources/bibles_json/kj/2samuel.json
pybible/resources/bibles_json/kj/2thessalonians.json
pybible/resources/bibles_json/kj/2timothy.json
pybible/resources/bibles_json/kj/3john.json
pybible/resources/bibles_json/kj/__init__.py
pybible/resources/bibles_json/kj/acts.json
pybible/resources/bibles_json/kj/amos.json
pybible/resources/bibles_json/kj/colossians.json
pybible/resources/bibles_json/kj/daniel.json
pybible/resources/bibles_json/kj/deuteronomy.json
pybible/resources/bibles_json/kj/ecclesiastes.json
pybible/resources/bibles_json/kj/ephesians.json
pybible/resources/bibles_json/kj/esther.json
pybible/resources/bibles_json/kj/exodus.json
pybible/resources/bibles_json/kj/ezekiel.json
pybible/resources/bibles_json/kj/ezra.json
pybible/resources/bibles_json/kj/galatians.json
pybible/resources/bibles_json/kj/genesis.json
pybible/resources/bibles_json/kj/habakkuk.json
pybible/resources/bibles_json/kj/haggai.json
pybible/resources/bibles_json/kj/hebrews.json
pybible/resources/bibles_json/kj/hosea.json
pybible/resources/bibles_json/kj/isaiah.json
pybible_cli-1.2.5.dist-info/LICENSE
pybible_cli-1.2.5.dist-info/METADATA
pybible_cli-1.2.5.dist-info/WHEEL
pybible_cli-1.2.5.dist-info/entry_points.txt
pybible_cli-1.2.5.dist-info/top_level.txt
pybible_cli-1.2.5.dist-info/RECORD
