Metadata-Version: 2.1
Name: pybible-cli
Version: 1.2.5
Summary: Bible reference CLI application
Home-page: https://github.com/vitorpio/pybible-cli
Author: Vitor Pio
Author-email: vitormarquespio@gmail.com
License: MIT License
Platform: UNKNOWN
Classifier: License :: OSI Approved :: MIT License
Classifier: Programming Language :: Python :: 3
Classifier: Programming Language :: Python :: 3.6
Classifier: Programming Language :: Python :: 3.7
Classifier: Programming Language :: Python :: 3.8
